{"id": "1000771", "question": "怎么理解分位数回归quantile regression的目标函数？", "description": "<div class=\"col-md-11 col-xs-10\"><p>怎么理解分位数回归quantile regression的目标函数？</p></div>", "viewer": 13351, "tags": ["统计/机器学习", "回归分析"], "answers": [{"lvl1_answer": "<div class=\"col-md-11 col-xs-10 p-r\"><p>Quantile Regression可以看作广义的LAD Regression.</p><p>假设$\\text{y}=(y_1,y_2,\\cdots, y_n)$为真实值，$\\hat{\\text{y}}=(\\hat{y_1},\\hat{y_2},\\cdots,\\hat{y_n})$为预测值，那么参数为$q$的Quantile Regression的目标函数为</p><p>$$L_q(\\text{y},\\hat{\\text{y}})=\\frac{1}{n}(1-q)\\sum_{i:\\hat{y_i}\\geq y_i}(\\hat{y_i} - y_i)+\\frac{1}{n}q\\sum_{j:\\hat{y_j}&lt; y_j}(y_j-\\hat{y_j} )$$</p><p>当$q=0.5$时，Quantile Regression就退化为LAD Regression，也就是所谓的中位数回归。</p><p>$$L_{0.5}(\\text{y},\\hat{\\text{y}})=\\frac{1}{2n}\\sum_{i=1}^n|\\hat{y_i}-y_i|$$.</p><p>当$q&gt;0.5$时，目标函数$L_q$对预测值偏小的结果惩罚更大。</p><p>当$q&lt;0.5$时，目标函数$L_q$对预测值偏大的结果惩罚更大。</p><p><br/></p></div>", "lvl2_answer": ["第一个公式里的$\\hat y_i-y_i$是括号还是绝对值符号？", "括号和绝对值一样呀，你看求和下的条件"]}]}