{"id": "1000732", "question": "tf.placeholder和tf.variable什么区别？", "description": "<div class=\"col-md-11 col-xs-10\"><p>最近开始学习tensorflow。一开始就有点懵，这个tf.placeholder和tf.variable有什么区别？感觉都是声明变量用的。</p><p>有知道的朋友可以具体解释一下吗？谢谢！</p></div>", "viewer": 9836, "tags": ["统计/机器学习", "Python", "TensorFlow"], "answers": [{"lvl1_answer": "<div class=\"col-md-11 col-xs-10 p-r\"><p>tf.placeholder在声明的时候不需要初始化的数值，只需要声明类型和维数，例如</p><pre><code class=\"python\">x = tf.placeholder(tf.float32, shape=(None, 1024))</code></pre><p>tf.placeholder是为了方便定义神经网络结构，所以可以看作是符号变量。<span style=\"font-weight: bold;\">tf.placeholder通常是在训练session开始后，存放输入样本的。</span></p><p><br/></p><p>tf.Variable在声明的时候必须要有初始的数值。例如</p><pre><code class=\"python\">weights = tf.Variable(tf.random_normal([784, 200], stddev=0.35),name=\"weights\")\nbiases = tf.Variable(tf.zeros([200]), name=\"biases\")</code></pre><p><span style=\"font-weight: bold;\">tf.Variable通常是存放weight和bias，然后会不停地被更新，所以说是variable。</span></p><p><span style=\"font-weight: bold;\"><br/></span></p></div>", "lvl2_answer": []}]}