{"id": "1001356", "question": "泊松回归（poission regression）的损失函数是什么？", "description": "<div class=\"col-md-11 col-xs-10\"><p>泊松回归（poission regression）的损失函数是什么？</p><p>谢谢！</p><p><br/></p></div>", "viewer": 7320, "tags": ["统计/机器学习", "回归分析", "损失函数"], "answers": [{"lvl1_answer": "<div class=\"col-md-11 col-xs-10 p-r\"><p><span style=\"font-size: 14px;\">怎么说呢，CS的人搞机器学习的时候，喜欢用损失函数（想要最小化）；统计的人搞机器学习的时候，一般都是通过式子推导到likelihood（想要最大化）。</span></p><p><span style=\"font-size: 14px;\">所以常常用likelihood取负数或者log likelihood取负数来表示损失函数。</span></p><p><span style=\"font-size: 14px;\">对于这里的poisson regression我们也是这样处理的。</span><span style=\"font-size: 14px;\">它的损失函数就是$-\\log (L(\\theta))$。具体而言，就是</span></p><p><span style=\"font-size: 14px;\">$$\\text{Cost}(\\theta)=-\\log (L(\\theta))=-\\sum_{i=1}^n\\left(y_i\\theta^T x_i -e^{\\theta^T} x_i\\right)$$</span></p><p><span style=\"font-size: 14px;\">其中$n$是样本个数，$y_i$真实值，$\\theta$是$p$元向量，$p$是特征的个数。</span></p><p><br/></p></div>", "lvl2_answer": []}]}