{"id": "1003457", "question": "今天明天都下雨的概率", "description": "<div class=\"col-md-11 col-xs-10\"><p>今天下雨的概率是p，明天下雨的概率是q，今天或者明天下雨的概率是m，今天和明天都下雨的概率是多少？</p><p><br/></p><p>今天下雨        p</p><p>今天不下雨    1-p</p><p>明天下雨        q</p><p>明天不下雨    1-q</p><p>P(今天下雨, 明天下雨)=pq</p><p>P(今天不下雨,明天下雨 或 今天下雨，明天不下雨)=P(今天或者明天下雨) =p(1-q)+q(1-p) </p><p><br/></p><p>为什么解答中是用文氏图 p+q-m 求 今天和明天都下雨的概率？</p><p><br/></p><p><br/></p></div>", "viewer": 3540, "tags": ["数学", "概率论"], "answers": [{"lvl1_answer": "<div class=\"col-md-11 col-xs-10 p-r\"><p>不太清楚你说的“解答”是什么意思</p><p>但是根据题意，今天和明天都下雨的概率是$p+q-m$，这个是对的。</p><p><br/></p><p>你假设了今天下雨和明天下雨是独立的，这显然太草率了，否则你就可以根据$p$和$q$直接推导出</p><p>$$m=1-(1-p)(1-q)=p+q-pq$$</p></div>", "lvl2_answer": []}]}